epiinfo/.EICSMeans.py.swp
epiinfo/BigDouble.py
epiinfo/CSUtilities.py
epiinfo/EICSMeans.py
epiinfo/EICSTables.py
epiinfo/EncryptionDecryptionKeys.py
epiinfo/Frequencies.py
epiinfo/ImportData.py
epiinfo/LineList.py
epiinfo/LinearRegression.py
epiinfo/LogBinomialRegression.py
epiinfo/LogisticRegression.py
epiinfo/MakeSQLite.py
epiinfo/Means.py
epiinfo/RegressionUtilities.py
epiinfo/ResultsFormatting.py
epiinfo/TablesAnalysis.py
epiinfo/__init__.py
epiinfo/randata.py
epiinfo-1.2.0.18.dist-info/licenses/LICENSE
epiinfo-1.2.0.18.dist-info/METADATA
epiinfo-1.2.0.18.dist-info/WHEEL
epiinfo-1.2.0.18.dist-info/top_level.txt
epiinfo-1.2.0.18.dist-info/RECORD
