Metadata-Version: 2.4
Name: epiinfo
Version: 1.2.0.18
Summary: Epi Info: Import and analyze data
Home-page: https://github.com/Epi-Info/epiinfo
Author: John Copeland
Author-email: ita3@cdc.gov
License: Apache License 2.0
Project-URL: Homepage, https://github.com/Epi-Info/epiinfo
Requires-Python: >=3.10
License-File: LICENSE
Requires-Dist: scipy
Requires-Dist: ijson
Requires-Dist: pycryptodome
Dynamic: author-email
Dynamic: home-page
Dynamic: license-file
